{
  "name": "login",
  "version": 32,
  "source-key": {
    "type": "figma",
    "file": "9fkqGLo8hvv1XMCY20CgWQ",
    "node": "23:173",
    "version": "5190289953",
    "component-id": "b5ad6e7c72f35c6d2b60e8d5d2cf7d0d132335d5"
  },
  "default": "Login",
  "design": {
    "atoms": [
      {
        "type": "group",
        "id": "top_level",
        "root": "true"
      },
      {
        "type": "group",
        "id": "top_level_synth"
      },
      {
        "type": "vector",
        "id": "LoginVector"
      },
      {
        "type": "vector",
        "id": "LoginEllipse"
      }
    ],
    "modes": {
      "Login": {
        "rules": [
          {
            "id": "top_level",
            "drop-shadow": {
              "color": {
                "alpha": "0.24705882352941178",
                "hue": "0.0",
                "saturation": "0.0",
                "value": "0.0"
              },
              "blur": "4.0",
              "offset-x": "0.0",
              "offset-y": "4.0",
              "spread": "0.0",
              "blend-mode": "normal"
            },
            "is-structured": "false",
            "children": [
              "top_level_synth",
              "LoginVector"
            ],
            "clip-content": "false"
          },
          {
            "id": "top_level_synth",
            "opacity": "100.0",
            "size-constraints": {
              "width-constraints": {
                "sizing-mode": "shrink"
              },
              "height-constraints": {
                "sizing-mode": "shrink"
              }
            },
            "children": [
              "LoginEllipse"
            ],
            "item-spacing": "10.0",
            "clip-content": "false"
          },
          {
            "id": "LoginVector",
            "margin": "17.34375",
            "size-constraints": {
              "width-constraints": {
                "sizing-mode": "proportional",
                "value": "1.0"
              },
              "height-constraints": {
                "sizing-mode": "proportional",
                "value": "1.0"
              }
            },
            "vector-content": "login_vector.svg"
          },
          {
            "id": "LoginEllipse",
            "size-constraints": {
              "width-constraints": {
                "sizing-mode": "fixed",
                "value": "111.0"
              },
              "height-constraints": {
                "sizing-mode": "fixed",
                "value": "111.0"
              }
            },
            "vector-content": "login_ellipse.svg"
          }
        ]
      }
    }
  },
  "previews": [
    {
      "design": "Login",
      "size": {
        "width": 111.0,
        "height": 111.0
      }
    }
  ],
  "adin-component-search-paths": [],
  "image-search-paths": [],
  "vector-search-paths": []
}